tokenflood/__init__.py
tokenflood/analysis.py
tokenflood/cli.py
tokenflood/constants.py
tokenflood/cost.py
tokenflood/gradio.py
tokenflood/heuristic.py
tokenflood/io.py
tokenflood/logging.py
tokenflood/models/__init__.py
tokenflood/models/budget.py
tokenflood/models/divergence.py
tokenflood/models/endpoint_spec.py
tokenflood/models/error_data.py
tokenflood/models/heuristic_task.py
tokenflood/models/llm_request_data.py
tokenflood/models/load_type.py
tokenflood/models/messages.py
tokenflood/models/observation_spec.py
tokenflood/models/ping_request_data.py
tokenflood/models/run_spec.py
tokenflood/models/run_suite.py
tokenflood/models/token_cost_aware.py
tokenflood/models/token_set.py
tokenflood/models/util.py
tokenflood/models/validation_types.py
tokenflood/models/validators.py
tokenflood/networking.py
tokenflood/observer.py
tokenflood/runner.py
tokenflood/starter_pack.py
tokenflood/util.py
tokenflood-0.6.0.dist-info/METADATA
tokenflood-0.6.0.dist-info/WHEEL
tokenflood-0.6.0.dist-info/entry_points.txt
tokenflood-0.6.0.dist-info/licenses/LICENSE
tokenflood-0.6.0.dist-info/RECORD
