Metadata-Version: 2.4
Name: tokenflood
Version: 0.6.0
Summary: Tokenflood is a load testing framework for simulating arbitary loads on instruction-tuned LLMs.
License-Expression: MIT
License-File: LICENSE
Author: Thomas Werkmeister
Author-email: thomas@werkmeister.me
Requires-Python: >=3.11,<3.14
Classifier: Programming Language :: Python :: 3
Classifier: Operating System :: OS Independent
Requires-Dist: aiofiles (>=22.0,<25.0)
Requires-Dist: gradio (>=6.1.0,<7.0.0)
Requires-Dist: litellm (>=1.78.0,<2.0.0)
Requires-Dist: numpy (>=2.2.6)
Requires-Dist: pandas (>=2.3.3,<3.0.0)
Requires-Dist: plotly (>=6.5.0,<7.0.0)
Requires-Dist: pydantic (>=2.12.2,<3.0.0)
Requires-Dist: python-dotenv (>=1.1.1,<2.0.0)
Requires-Dist: rich (>=14.2.0,<15.0.0)
Requires-Dist: tokenizers (>=0.22.1,<0.23.0)
Requires-Dist: tqdm (>=4.67.1,<5.0.0)
Project-URL: Homepage, https://github.com/twerkmeister/tokenflood
Project-URL: Issues, https://github.com/twerkmeister/tokenflood/issues
